[
  {
    "strLabel": "\u5438\u5634Y\u8EF8",
    "u32Index": 1,
    "dbPosition": 27.050000000000001,
    "strNote": "\u4E0B\u8996\u89BA\u53D6\u50CF\u4F4D\u7F6E"
  },
  {
    "strLabel": "\u5438\u5634Z\u8EF8",
    "u32Index": 2,
    "dbPosition": 0,
    "strNote": "\u4E0B\u8996\u89BA\u53D6\u50CF\u4F4D\u7F6E"
  },
  {
    "strLabel": "\u690D\u91DDR\u8EF8",
    "u32Index": 3,
    "dbPosition": 268.07999999999998,
    "strNote": "\u653E\u6599\u4F4D"
  },
  {
    "strLabel": "\u690D\u91DDR\u8EF8",
    "u32Index": 4,
    "dbPosition": 178.08000000000001,
    "strNote": "\u690D\u91DD\u4F4D"
  },
  {
    "strLabel": "\u690D\u91DDZ\u8EF8",
    "u32Index": 5,
    "dbPosition": 12,
    "strNote": "\u653E\u6599\u4F4D"
  },
  {
    "strLabel": "\u690D\u91DDZ\u8EF8",
    "u32Index": 6,
    "dbPosition": 26,
    "strNote": "\u690D\u91DD\u4F4D"
  },
  {
    "strLabel": "Socket\u6AA2\u6E2C",
    "u32Index": 7,
    "dbPosition": 22,
    "strNote": "\u8F09\u76E4\u4F4D"
  },
  {
    "strLabel": "\u8F09\u76E4X\u8EF8",
    "u32Index": 8,
    "dbPosition": 137.17080000000001,
    "strNote": "028\u5DE6\u4E0A\u89D2\u5B54\u5230\u7167\u6A5F\u4E2D\u5FC3"
  },
  {
    "strLabel": "\u8F09\u76E4Y\u8EF8",
    "u32Index": 9,
    "dbPosition": 602.12300000000005,
    "strNote": "028\u5DE6\u4E0A\u89D2\u5B54\u5230\u7167\u6A5F\u4E2D\u5FC3"
  },
  {
    "strLabel": "\u8F09\u76E4X\u8EF8",
    "u32Index": 10,
    "dbPosition": 138.99100000000001,
    "strNote": "028\u5DE6\u4E0A\u89D2\u5B54\u5230\u690D\u91DD\u5634\u4E2D\u5FC3"
  },
  {
    "strLabel": "\u8F09\u76E4Y\u8EF8",
    "u32Index": 11,
    "dbPosition": 656.92499999999995,
    "strNote": "028\u5DE6\u4E0A\u89D2\u5B54\u5230\u690D\u91DD\u5634\u4E2D\u5FC3"
  },
  {
    "strLabel": "\u5438\u5634R\u8EF8",
    "u32Index": 12,
    "dbPosition": 91.349999999999994,
    "strNote": "\u81F3\u4E0A\u819B\u4F4D"
  },
  {
    "strLabel": "\u5438\u5634X\u8EF8",
    "u32Index": 13,
    "dbPosition": 495,
    "strNote": "\u81F3\u4E0A\u819B\u4F4D"
  },
  {
    "strLabel": "\u5438\u5634Y\u8EF8",
    "u32Index": 14,
    "dbPosition": 77.049999999999997,
    "strNote": "\u81F3\u4E0A\u819B\u4F4D"
  },
  {
    "strLabel": "\u5438\u5634Z\u8EF8",
    "u32Index": 15,
    "dbPosition": 36.700000000000003,
    "strNote": "\u81F3\u4E0A\u819B\u4F4D\u4E0A\u6599\u4F4D"
  }
]